deltas/__init__.py
deltas/about.py
deltas/apply.py
deltas/operations.py
deltas/util.py
deltas/algorithms/__init__.py
deltas/algorithms/diff_engine.py
deltas/algorithms/segment_matcher.py
deltas/algorithms/sequence_matcher.py
deltas/algorithms/tests/__init__.py
deltas/algorithms/tests/test_from_config.py
deltas/algorithms/tests/test_segment_matcher.py
deltas/algorithms/tests/test_sequence_matcher.py
deltas/segmenters/__init__.py
deltas/segmenters/functions.py
deltas/segmenters/paragraphs_sentences_and_whitespace.py
deltas/segmenters/segmenter.py
deltas/segmenters/segments.py
deltas/segmenters/tests/__init__.py
deltas/segmenters/tests/test_paragraphs_sentences_and_whitespace.py
deltas/segmenters/tests/test_segments.py
deltas/tests/__init__.py
deltas/tests/diff_and_replay.py
deltas/tests/diff_sequence.py
deltas/tests/test_apply.py
deltas/tests/test_util.py
deltas/tokenizers/__init__.py
deltas/tokenizers/cjk_tokenization.py
deltas/tokenizers/lexicon.py
deltas/tokenizers/lexicon_chars.py
deltas/tokenizers/text_split.py
deltas/tokenizers/token.py
deltas/tokenizers/tokenizer.py
deltas/tokenizers/wikitext_split.py
deltas/tokenizers/wikitext_split_w_cjk.py
deltas/tokenizers/tests/__init__.py
deltas/tokenizers/tests/test_text_split.py
deltas/tokenizers/tests/test_wikitext_split.py
deltas/tokenizers/tests/test_wikitext_split_w_cjk.py
deltas-0.7.0.dist-info/LICENSE
deltas-0.7.0.dist-info/METADATA
deltas-0.7.0.dist-info/WHEEL
deltas-0.7.0.dist-info/top_level.txt
deltas-0.7.0.dist-info/RECORD
